{"id": "gen9ou-1947619434", "p1": "GolurkofPrague", "p2": "sedman69", "format": "gen9ou", "log": "|j|\u2606GolurkofPrague\n|j|\u2606sedman69\n|t:|1695178563\n|gametype|singles\n|player|p1|GolurkofPrague|shauntal|1112\n|player|p2|sedman69|2|1140\n|teamsize|p1|6\n|teamsize|p2|6\n|gen|9\n|tier|[Gen 9] OU\n|rated|\n|rule|Sleep Clause Mod: Limit one foe put to sleep\n|rule|Species Clause: Limit one of each Pok\u00e9mon\n|rule|OHKO Clause: OHKO moves are banned\n|rule|Evasion Items Clause: Evasion items are banned\n|rule|Evasion Moves Clause: Evasion moves are banned\n|rule|Endless Battle Clause: Forcing endless battles is banned\n|rule|HP Percentage Mod: HP is shown in percentages\n|clearpoke\n|poke|p1|Tyranitar, F|\n|poke|p1|Houndstone, F|\n|poke|p1|Empoleon, M|\n|poke|p1|Mandibuzz, F|\n|poke|p1|Gliscor, F|\n|poke|p1|Ursaluna-Bloodmoon, M|\n|poke|p2|Garchomp, M|\n|poke|p2|Kingambit, M|\n|poke|p2|Torterra, M|\n|poke|p2|Sneasler, M|\n|poke|p2|Heatran, M|\n|poke|p2|Scream Tail|\n|teampreview\n|\n|t:|1695178583\n|start\n|switch|p1a: Gliscor|Gliscor, F, shiny|100/100\n|switch|p2a: Return of the King|Torterra, M|100/100\n|turn|1\n|\n|t:|1695178591\n|switch|p1a: Mandibuzz|Mandibuzz, F, shiny|100/100\n|-terastallize|p2a: Return of the King|Steel\n|move|p2a: Return of the King|Shell Smash|p2a: Return of the King\n|-unboost|p2a: Return of the King|def|1\n|-unboost|p2a: Return of the King|spd|1\n|-boost|p2a: Return of the King|atk|2\n|-boost|p2a: Return of the King|spa|2\n|-boost|p2a: Return of the King|spe|2\n|\n|upkeep\n|turn|2\n|\n|t:|1695178604\n|move|p2a: Return of the King|Rock Blast|p1a: Mandibuzz|[miss]\n|-miss|p2a: Return of the King|p1a: Mandibuzz\n|move|p1a: Mandibuzz|Foul Play|p2a: Return of the King\n|-damage|p2a: Return of the King|0 fnt\n|faint|p2a: Return of the King\n|\n|upkeep\n|c|\u2606sedman69|WHAT\n|c|\u2606sedman69|WHATaohdtglsanbdkgnsldkngklsdngknsfdklgnsfdklgnskldngikonqaeuifhaiehnuiwsls\n|c|\u2606sedman69|WHAT THE HELL\n|c|\u2606sedman69|im good\n|-message|sedman69 forfeited.\n|\n|win|GolurkofPrague\n|raw|GolurkofPrague's rating: 1112 &rarr; <strong>1139</strong><br />(+27 for winning)\n|raw|sedman69's rating: 1140 &rarr; <strong>1113</strong><br />(-27 for losing)\n|c|\u2606GolurkofPrague|It calculates using your attack stat\n|c|\u2606sedman69|i know what foul play does\n|c|\u2606sedman69|it was more rock blast missing\n", "uploadtime": 1695178631, "views": 6, "p1id": "golurkofprague", "p2id": "sedman69", "formatid": "gen9ou", "rating": 1113, "private": 0, "password": ""}